examples/__init__.py
examples/hello-world-class.py
examples/hello-world-func.py
examples/hello-world.py
examples/multi-path.py
examples/pipeline.py
pyperunner/__init__.py
pyperunner/decorator.py
pyperunner/pipeline.py
pyperunner/result.py
pyperunner/task.py
pyperunner/util.py
pyperunner/version.py
pyperunner/dag/__init__.py
pyperunner/dag/dagascii.py
pyperunner/runner/__init__.py
pyperunner/runner/logger.py
pyperunner/runner/multiprocess.py
pyperunner-0.1.0rc1.dist-info/LICENSE
pyperunner-0.1.0rc1.dist-info/METADATA
pyperunner-0.1.0rc1.dist-info/WHEEL
pyperunner-0.1.0rc1.dist-info/top_level.txt
pyperunner-0.1.0rc1.dist-info/RECORD
