Metadata-Version: 2.1
Name: pyperunner
Version: 0.1.0rc1
Summary: Yet another ETL pipeline runner for python, using multiprocessing and directed acyclic graphs.
Home-page: https://github.com/glichtner/pyperunner/
Author: Gregor Lichtner
Maintainer: Gregor Lichtner
License: GNU General Public License v3
Keywords: pyperunner
Platform: UNKNOWN
Classifier: Development Status :: 3 - Alpha
Classifier: Intended Audience :: Developers
Classifier: Programming Language :: Python :: 3.6
Classifier: Programming Language :: Python :: 3.7
Classifier: Programming Language :: Python :: 3.8
Classifier: Programming Language :: Python :: 3.9
Requires-Dist: grandalf (==0.6)
Requires-Dist: networkx (==2.5)
Requires-Dist: coloredlogs (==15.0)
Requires-Dist: pydot (==1.4.1)
Requires-Dist: joblib (==0.17.0)
